spotifysaver/__init__.py
spotifysaver/__main__.py
spotifysaver/api/__init__.py
spotifysaver/api/app.py
spotifysaver/api/config.py
spotifysaver/api/examples.py
spotifysaver/api/main.py
spotifysaver/api/README.md
spotifysaver/api/routers/__init__.py
spotifysaver/api/routers/download.py
spotifysaver/api/schemas.py
spotifysaver/api/services/__init__.py
spotifysaver/api/services/download_service.py
spotifysaver/cli/__init__.py
spotifysaver/cli/cli.py
spotifysaver/cli/commands/__init__.py
spotifysaver/cli/commands/download/__init__.py
spotifysaver/cli/commands/download/album.py
spotifysaver/cli/commands/download/download.py
spotifysaver/cli/commands/download/playlist.py
spotifysaver/cli/commands/download/track.py
spotifysaver/cli/commands/init.py
spotifysaver/cli/commands/inspect/__init__.py
spotifysaver/cli/commands/inspect/album_info.py
spotifysaver/cli/commands/inspect/inspect.py
spotifysaver/cli/commands/inspect/playlist_info.py
spotifysaver/cli/commands/inspect/track_info.py
spotifysaver/cli/commands/log/__init__.py
spotifysaver/cli/commands/log/log.py
spotifysaver/cli/commands/version.py
spotifysaver/config/__init__.py
spotifysaver/config/setting_environment.py
spotifysaver/downloader/__init__.py
spotifysaver/downloader/image_downloader.py
spotifysaver/downloader/youtube_downloader.py
spotifysaver/downloader/youtube_downloader_for_cli.py
spotifysaver/enums/__init__.py
spotifysaver/enums/audio_formats_enum.py
spotifysaver/enums/bitrates_enum.py
spotifysaver/metadata/__init__.py
spotifysaver/metadata/music_file_metadata.py
spotifysaver/metadata/nfo_generator.py
spotifysaver/models/__init__.py
spotifysaver/models/album.py
spotifysaver/models/artist.py
spotifysaver/models/playlist.py
spotifysaver/models/track.py
spotifysaver/services/__init__.py
spotifysaver/services/errors/errors.py
spotifysaver/services/lrclib_api.py
spotifysaver/services/score_match_calculator.py
spotifysaver/services/spotify_api.py
spotifysaver/services/youtube_api.py
spotifysaver-0.6.3.dist-info/entry_points.txt
spotifysaver-0.6.3.dist-info/LICENSE
spotifysaver-0.6.3.dist-info/METADATA
spotifysaver-0.6.3.dist-info/WHEEL
spotifysaver-0.6.3.dist-info/RECORD
