Metadata-Version: 2.3
Name: spotifysaver
Version: 0.6.3
Summary: Download Spotify tracks/albums with metadata via YouTube Music (Perfect for Jellyfin libraries!)
License: MIT
Keywords: spotify,youtube-music,music-downloader,jellyfin,metadata,cli-tool
Author: Gabriel Baute
Author-email: gabrielbaute@gmail.com
Requires-Python: >=3.9,<4.0
Classifier: Development Status :: 4 - Beta
Classifier: Environment :: Console
Classifier: Intended Audience :: End Users/Desktop
Classifier: License :: OSI Approved :: MIT License
Classifier: Programming Language :: Python :: 3
Classifier: Programming Language :: Python :: 3.9
Classifier: Programming Language :: Python :: 3.10
Classifier: Programming Language :: Python :: 3.11
Classifier: Programming Language :: Python :: 3.12
Classifier: Programming Language :: Python :: 3.13
Classifier: Programming Language :: Python :: 3.8
Classifier: Topic :: Multimedia :: Sound/Audio
Classifier: Topic :: Utilities
Requires-Dist: click (>=8.1.8,<9.0.0)
Requires-Dist: fastapi (>=0.115.14,<0.116.0)
Requires-Dist: mutagen (>=1.47.0,<2.0.0)
Requires-Dist: pydantic (>=2.11.9,<3.0.0)
Requires-Dist: python-dotenv (>=1.1.1,<2.0.0)
Requires-Dist: requests (>=2.32.5,<3.0.0)
Requires-Dist: spotipy (>=2.25.1,<3.0.0)
Requires-Dist: uvicorn[standard] (>=0.34.0,<0.35.0)
Requires-Dist: yt-dlp (>=2025.10.14,<2026.0.0)
Requires-Dist: ytmusicapi (>=1.10.3,<2.0.0)
Project-URL: Documentation, https://deepwiki.com/gabrielbaute/spotify-saver
Project-URL: Homepage, https://github.com/gabrielbaute/spotify-saver
Project-URL: Repository, https://github.com/gabrielbaute/spotify-saver
